README.md
setup.py
fs_cli/__init__.py
fs_cli/cli.py
fs_cli/commands.py
fs_cli/config.py
fs_cli.egg-info/PKG-INFO
fs_cli.egg-info/SOURCES.txt
fs_cli.egg-info/dependency_links.txt
fs_cli.egg-info/entry_points.txt
fs_cli.egg-info/requires.txt
fs_cli.egg-info/top_level.txt