Metadata-Version: 2.1
Name: fs-cli
Version: 0.3
Summary: Fogstream CLI
Home-page: https://github.com/fogstream/fs-cli
Author: Dmitry Kotov
Author-email: dmitrii.kotov@fogstream.com
License: UNKNOWN
Platform: UNKNOWN
Classifier: Programming Language :: Python :: 3
Classifier: License :: OSI Approved :: MIT License
Classifier: Operating System :: POSIX
